linteum_verba/__init__.py
linteum_verba/config_manager.py
linteum_verba/controller.py
linteum_verba/controller_fixed.py
linteum_verba/event_bus.py
linteum_verba/logging_config.py
linteum_verba/main.py
linteum_verba/main_fixed.py
linteum_verba/model.py
linteum_verba/model_fixed.py
linteum_verba/sample.py
linteum_verba/simple_sample.py
linteum_verba/view.py
linteum_verba/local packages/imitatio_ostendendi/__init__.py
linteum_verba/local packages/imitatio_ostendendi/constants.py
linteum_verba/local packages/imitatio_ostendendi/widgets.py
linteum_verba/local packages/imitatio_ostendendi/widgets/__init__.py
linteum_verba/local packages/imitatio_ostendendi/widgets/base.py
linteum_verba/local packages/imitatio_ostendendi/widgets/buttons.py
linteum_verba/local packages/imitatio_ostendendi/widgets/entry.py
linteum_verba/local packages/imitatio_ostendendi/widgets/frames.py
linteum_verba/local packages/imitatio_ostendendi/widgets/text.py
linteum_verba-1.0.0.dist-info/METADATA
linteum_verba-1.0.0.dist-info/WHEEL
linteum_verba-1.0.0.dist-info/entry_points.txt
linteum_verba-1.0.0.dist-info/top_level.txt
linteum_verba-1.0.0.dist-info/RECORD
